Metadata-Version: 2.1
Name: jamesisconfused
Version: 1.99.5
Summary: More poetry to the people! One cannot live on water but one can live on poetry (if there is also food ... and also water and whatnot).
Author: Ich B. EineBerliner
Author-email: jaymz@kommunpoet.se
Classifier: Programming Language :: Python :: 3
Classifier: License :: OSI Approved :: MIT License
Classifier: Operating System :: OS Independent
Requires-Python: >=3.6
